db_refresh
