Metadata-Version: 1.0
Name: db-refresh
Version: 0.3
Summary: refresh db
Home-page: https://www.test.com
Author: EranArtzi
Author-email: eartzi@gmail.com
License: UNKNOWN
Platform: UNKNOWN
